Metadata-Version: 1.0
Name: g-b-probability
Version: 0.1
Summary: Gaussian & Binomial distributions
Home-page: UNKNOWN
Author: Apu Chandraw
Author-email: apu3660@gmail.com
License: UNKNOWN
Platform: UNKNOWN
